superconfig/__init__.py
superconfig/superconf.py
superconfig/parsers/__init__.py
superconfig/parsers/env_parser.py
superconfig/parsers/ini_parser.py
superconfig/parsers/json_parser.py
superconfig/parsers/yaml_parser.py
superconfig/utilities/__init__.py
superconfig/utilities/dtypes.py
superconfig/utilities/parser_utils.py
Super_Config-0.0.3.dist-info/METADATA
Super_Config-0.0.3.dist-info/WHEEL
Super_Config-0.0.3.dist-info/top_level.txt
Super_Config-0.0.3.dist-info/RECORD
