Metadata-Version: 2.1
Name: Super-Config
Version: 0.0.3
Summary: Parse bank cheques
Home-page: https://github.com/ajkdrag/Super-Config
Author: ajkdrag
Author-email: 
Maintainer: ajkdrag
Maintainer-email: 
License: Apache Software License 2.0
Keywords: superconfig,Super-Config,Super_Config,super_config
Platform: UNKNOWN
Classifier: Intended Audience :: Developers
Classifier: Programming Language :: Python :: 3.8
Classifier: Programming Language :: Python :: 3.9
Requires-Dist: pyyaml
Requires-Dist: smart-open
Provides-Extra: all
Requires-Dist: smart-open[s3] ; extra == 'all'
Requires-Dist: smart-open[gcs] ; extra == 'all'
Provides-Extra: gcs
Requires-Dist: smart-open[gcs] ; extra == 'gcs'
Provides-Extra: s3
Requires-Dist: smart-open[s3] ; extra == 's3'
Provides-Extra: smart_open_gcs_
Requires-Dist: smart-open[gcs] ; extra == 'smart_open_gcs_'
Provides-Extra: smart_open_s3_
Requires-Dist: smart-open[s3] ; extra == 'smart_open_s3_'
